clearjunction_api/__init__.py
clearjunction_api/api.py
clear_junction_api_wrapper-0.0.1.dist-info/METADATA
clear_junction_api_wrapper-0.0.1.dist-info/WHEEL
clear_junction_api_wrapper-0.0.1.dist-info/top_level.txt
clear_junction_api_wrapper-0.0.1.dist-info/RECORD
